{"assets":{"CFF255043BCBDD010321137371C22FE7":{"type":"texture","index":1,"assetRequest":{"type":"slide","state":"contents","slide":"none"},"url":{"native":"assets\/12BD5AF9-785E-4D9F-89D3-4E2B633E04AF.pdf"},"width":569,"height":132},"15B6FB6E2B3718897415A5DD6FF7078E":{"type":"texture","index":9,"assetRequest":{"type":"slide","state":"contents","slide":"none"},"url":{"native":"assets\/12BD5AF9-785E-4D9F-89D3-4E2B633E04AF.pdf"},"width":1920,"height":1080},"D8EEC255404DD97E514706B0FC780AF7":{"url":{"native":"assets\/12BD5AF9-785E-4D9F-89D3-4E2B633E04AF.pdf"},"height":1071.5928955078125,"movie":"CelebFeedGesture.mov-0.0000-10.6118","width":567.49139404296875,"type":"texture","assetRequest":{"type":"slide","state":"contents","slide":"none"},"index":7},"C25C25FF361FB24FC35F6B120D2F252D":{"type":"texture","index":0,"assetRequest":{"type":"slide","state":"contents","slide":"none"},"url":{"native":"assets\/12BD5AF9-785E-4D9F-89D3-4E2B633E04AF.pdf"},"width":1920,"height":1080},"95C393E5DF3E73B6B77ECA874AAFC7A9":{"type":"texture","index":6,"assetRequest":{"type":"slide","state":"contents","slide":"none"},"url":{"native":"assets\/12BD5AF9-785E-4D9F-89D3-4E2B633E04AF.pdf"},"width":571,"height":1075},"3F2A874332E05EB3B623F716EC48D200":{"type":"texture","index":5,"assetRequest":{"type":"slide","state":"contents","slide":"none"},"url":{"native":"assets\/12BD5AF9-785E-4D9F-89D3-4E2B633E04AF.pdf"},"width":87,"height":19},"2E3956B3E95E6176301E998B6FA0DA28":{"type":"texture","index":4,"assetRequest":{"type":"slide","state":"contents","slide":"none"},"url":{"native":"assets\/12BD5AF9-785E-4D9F-89D3-4E2B633E04AF.pdf"},"width":531,"height":942},"46CC28EA4F4ABA1C058F0FD882325C11":{"type":"texture","index":8,"assetRequest":{"type":"slide","state":"contents","slide":"none"},"url":{"native":"assets\/12BD5AF9-785E-4D9F-89D3-4E2B633E04AF.pdf"},"width":1920,"height":1080},"33E3B8D6F9BB46952212E3A2C137759B":{"type":"texture","index":2,"assetRequest":{"type":"slide","state":"contents","slide":"none"},"url":{"native":"assets\/12BD5AF9-785E-4D9F-89D3-4E2B633E04AF.pdf"},"width":685,"height":215},"39A9887790E8F93E6D3B349BEE714FFC":{"type":"texture","index":3,"assetRequest":{"type":"slide","state":"contents","slide":"none"},"url":{"native":"assets\/12BD5AF9-785E-4D9F-89D3-4E2B633E04AF.pdf"},"width":571,"height":1075},"CelebFeedGesture.mov-0.0000-10.6118":{"type":"video","index":0,"assetRequest":{"type":"slide","state":"contents","slide":"none"},"url":{"web":"assets\/CelebFeedGesture.mov-0.0000-10.6118.mov","native":"assets\/CelebFeedGesture.mov-0.0000-10.6118.mov"},"width":752,"height":1420}},"events":[{"effects":[{"beginTime":0,"baseLayer":{"animations":[],"initialState":{"affineTransform":[1,0,0,1,0,0],"masksToBounds":false,"rotation":0,"scale":1,"position":{"pointX":1072.2609252929688,"pointY":561.15006256103516},"width":571,"sublayerTransform":[1,0,0,0,0,1,0,0,0,0,1,0,0,0,0,1],"contentsRect":{"y":0,"x":0,"width":1,"height":1},"opacity":1,"edgeAntialiasingMask":251658240,"height":1075,"hidden":false,"anchorPoint":{"pointX":0.5,"pointY":0.5}},"objectID":"19EAA004-48BC-4AB6-8E98-2574FCF9A739","layers":[{"animations":[],"initialState":{"affineTransform":[1,0,0,1,0,0],"masksToBounds":false,"rotation":0,"scale":1,"position":{"pointX":173.23907470703125,"pointY":516.34993743896484},"width":571,"sublayerTransform":[1,0,0,0,0,1,0,0,0,0,1,-0.00035007912466775983,0,0,0,1],"contentsRect":{"y":0,"x":0,"width":1,"height":1},"opacity":1,"edgeAntialiasingMask":251658240,"height":1075,"hidden":false,"anchorPoint":{"pointX":0.303395927683067,"pointY":0.48032552319903704}},"layers":[{"animations":[{"timeOffset":0,"beginTime":1e-100,"repeatCount":0,"animations":[{"timeOffset":0,"from":{"scalar":false},"beginTime":0,"repeatCount":0,"fillMode":"removed","property":"hidden","autoreverses":false,"duration":0.01,"to":{"scalar":false}},{"timeOffset":0,"from":{"scalar":true},"beginTime":0,"repeatCount":0,"fillMode":"removed","property":"isPlaying","autoreverses":false,"duration":0.01,"to":{"scalar":true}}],"fillMode":"both","autoreverses":false,"duration":0.01}],"layers":[],"texturedRectangle":{"isBackgroundTexture":true,"singleTextureOpacity":1,"textureType":5,"textBaseline":0,"textXHeight":0,"isVerticalText":false},"initialState":{"affineTransform":[1,0,0,1,0,0],"masksToBounds":false,"rotation":0,"scale":1,"position":{"pointX":283.73907470703125,"pointY":535.84993743896484},"width":571,"sublayerTransform":[1,0,0,0,0,1,0,0,0,0,1,0,0,0,0,1],"contentsRect":{"y":0,"x":0,"width":1,"height":1},"opacity":1,"edgeAntialiasingMask":0,"height":1075,"hidden":false,"anchorPoint":{"pointX":0.5,"pointY":0.5}},"texture":"39A9887790E8F93E6D3B349BEE714FFC"}]}]},"effects":[{"beginTime":0,"baseLayer":{"animations":[],"initialState":{"affineTransform":[1,0,0,1,0,0],"masksToBounds":false,"rotation":0,"scale":1,"position":{"pointX":1070.5066223144531,"pointY":559.44651031494141},"width":567.49139404296875,"sublayerTransform":[1,0,0,0,0,1,0,0,0,0,1,0,0,0,0,1],"contentsRect":{"y":0,"x":0,"width":1,"height":1},"opacity":1,"edgeAntialiasingMask":251658240,"height":1071.5928955078125,"hidden":false,"anchorPoint":{"pointX":0.5,"pointY":0.5}},"objectID":"19EAA004-48BC-4AB6-8E98-2574FCF9A739","layers":[{"animations":[],"layers":[],"texturedRectangle":{"isBackgroundTexture":true,"singleTextureOpacity":1,"textureType":5,"textBaseline":0,"textXHeight":0,"isVerticalText":false},"initialState":{"affineTransform":[1,0,0,1,0,0],"masksToBounds":false,"rotation":0,"scale":1,"position":{"pointX":283.73907470703125,"pointY":535.84993743896484},"width":571,"sublayerTransform":[1,0,0,0,0,1,0,0,0,0,1,0,0,0,0,1],"contentsRect":{"y":0,"x":0,"width":1,"height":1},"opacity":1,"edgeAntialiasingMask":0,"height":1075,"hidden":true,"anchorPoint":{"pointX":0.5,"pointY":0.5}},"texture":"95C393E5DF3E73B6B77ECA874AAFC7A9"},{"animations":[],"layers":[],"isVideoLayer":true,"initialState":{"affineTransform":[1,0,0,1,0,0],"masksToBounds":false,"rotation":0,"scale":1,"position":{"pointX":283.74569702148438,"pointY":535.79644775390625},"width":567.49139404296875,"sublayerTransform":[1,0,0,0,0,1,0,0,0,0,1,0,0,0,0,1],"contentsRect":{"y":0,"x":0,"width":1,"height":1},"opacity":1,"edgeAntialiasingMask":251658240,"height":1071.5928955078125,"hidden":false,"anchorPoint":{"pointX":0.5,"pointY":0.5}},"texture":"D8EEC255404DD97E514706B0FC780AF7"}]},"effects":[],"movie":{"startTime":0,"volume":1,"endTime":10.611833572387695,"isStreaming":false,"isAudioOnly":false,"asset":"CelebFeedGesture.mov-0.0000-10.6118"},"duration":0,"type":"buildIn","attributes":{"direction":0},"name":"renderMovie","objectID":"19EAA004-48BC-4AB6-8E98-2574FCF9A739"}],"duration":0.01,"type":"buildIn","attributes":{"direction":0},"name":"apple:movie-start","objectID":"19EAA004-48BC-4AB6-8E98-2574FCF9A739"}],"automaticPlay":true,"hyperlinks":[],"accessibility":[{"text":"IMG_1015.png","targetRectangle":{"y":70.938201904296875,"x":1343.110107421875,"width":528.52032470703125,"height":938.12359619140625}},{"text":"Validation at low \\u2028fidelities for high ROI","targetRectangle":{"y":52.395637512207031,"x":70.882247924804688,"width":569.07839999999999,"height":144}},{"text":"• • • •","targetRectangle":{"y":1002,"x":71.413619995117188,"width":88.23599999999999,"height":46}},{"text":"A motion prototype meant to convey nuanced gestural interactions. After handing off to a developer we were able to test a coded prototype within the week. ","targetRectangle":{"y":219.5,"x":71.427436828613281,"width":689.32799999999997,"height":230}}],"baseLayer":{"animations":[],"initialState":{"affineTransform":[1,0,0,1,0,0],"masksToBounds":false,"rotation":0,"scale":1,"position":{"pointX":960,"pointY":540},"width":1920,"sublayerTransform":[1,0,0,0,0,1,0,0,0,0,1,0,0,0,0,1],"contentsRect":{"y":0,"x":0,"width":1,"height":1},"opacity":1,"edgeAntialiasingMask":251658240,"height":1080,"hidden":false,"anchorPoint":{"pointX":0.5,"pointY":0.5}},"layers":[{"animations":[],"initialState":{"affineTransform":[1,0,0,1,0,0],"masksToBounds":false,"rotation":0,"scale":1,"position":{"pointX":960,"pointY":540},"width":1920,"sublayerTransform":[1,0,0,0,0,1,0,0,0,0,1,0,0,0,0,1],"contentsRect":{"y":0,"x":0,"width":1,"height":1},"opacity":1,"edgeAntialiasingMask":251658240,"height":1080,"hidden":false,"anchorPoint":{"pointX":0.5,"pointY":0.5}},"layers":[{"animations":[],"initialState":{"affineTransform":[1,0,0,1,0,0],"masksToBounds":false,"rotation":0,"scale":1,"position":{"pointX":960,"pointY":540},"width":1920,"sublayerTransform":[1,0,0,0,0,1,0,0,0,0,1,0,0,0,0,1],"contentsRect":{"y":0,"x":0,"width":1,"height":1},"opacity":1,"edgeAntialiasingMask":251658240,"height":1080,"hidden":false,"anchorPoint":{"pointX":0.5,"pointY":0.5}},"layers":[{"animations":[],"layers":[],"texturedRectangle":{"isBackgroundTexture":true,"singleTextureOpacity":1,"textureType":1,"textBaseline":0,"textXHeight":0,"isVerticalText":false},"initialState":{"affineTransform":[1,0,0,1,0,0],"masksToBounds":false,"rotation":0,"scale":1,"position":{"pointX":960,"pointY":540},"width":1920,"sublayerTransform":[1,0,0,0,0,1,0,0,0,0,1,0,0,0,0,1],"contentsRect":{"y":0,"x":0,"width":1,"height":1},"opacity":1,"edgeAntialiasingMask":0,"height":1080,"hidden":false,"anchorPoint":{"pointX":0.5,"pointY":0.5}},"texture":"C25C25FF361FB24FC35F6B120D2F252D"}]}]},{"animations":[],"initialState":{"affineTransform":[1,0,0,1,0,0],"masksToBounds":false,"rotation":0,"scale":1,"position":{"pointX":960,"pointY":540},"width":1920,"sublayerTransform":[1,0,0,0,0,1,0,0,0,0,1,0,0,0,0,1],"contentsRect":{"y":0,"x":0,"width":1,"height":1},"opacity":1,"edgeAntialiasingMask":251658240,"height":1080,"hidden":false,"anchorPoint":{"pointX":0.5,"pointY":0.5}},"layers":[{"animations":[],"initialState":{"affineTransform":[1,0,0,1,0,0],"masksToBounds":false,"rotation":0,"scale":1,"position":{"pointX":351.38224792480469,"pointY":112.39563751220703},"width":569,"sublayerTransform":[1,0,0,0,0,1,0,0,0,0,1,0,0,0,0,1],"contentsRect":{"y":0,"x":0,"width":1,"height":1},"opacity":1,"edgeAntialiasingMask":251658240,"height":132,"hidden":false,"anchorPoint":{"pointX":0.5,"pointY":0.5}},"layers":[{"animations":[],"layers":[],"texturedRectangle":{"singleTextureOpacity":1,"textXHeight":0.21887500000000001,"textBaseline":0.88619488802823143,"isBackgroundTexture":true,"isVerticalText":false,"textColor":[0,0,0,1],"textureType":6},"initialState":{"affineTransform":[1,0,0,1,0,0],"masksToBounds":false,"rotation":0,"scale":1,"position":{"pointX":286.61775207519531,"pointY":84.604362487792969},"width":569,"sublayerTransform":[1,0,0,0,0,1,0,0,0,0,1,0,0,0,0,1],"contentsRect":{"y":0,"x":0,"width":1,"height":1},"opacity":1,"edgeAntialiasingMask":0,"height":132,"hidden":false,"anchorPoint":{"pointX":0.5,"pointY":0.5}},"texture":"CFF255043BCBDD010321137371C22FE7"}]}]},{"animations":[],"initialState":{"affineTransform":[1,0,0,1,0,0],"masksToBounds":false,"rotation":0,"scale":1,"position":{"pointX":960,"pointY":540},"width":1920,"sublayerTransform":[1,0,0,0,0,1,0,0,0,0,1,0,0,0,0,1],"contentsRect":{"y":0,"x":0,"width":1,"height":1},"opacity":1,"edgeAntialiasingMask":251658240,"height":1080,"hidden":false,"anchorPoint":{"pointX":0.5,"pointY":0.5}},"layers":[{"animations":[],"initialState":{"affineTransform":[1,0,0,1,0,0],"masksToBounds":false,"rotation":0,"scale":1,"position":{"pointX":409.92743682861328,"pointY":323},"width":685,"sublayerTransform":[1,0,0,0,0,1,0,0,0,0,1,0,0,0,0,1],"contentsRect":{"y":0,"x":0,"width":1,"height":1},"opacity":1,"edgeAntialiasingMask":251658240,"height":215,"hidden":false,"anchorPoint":{"pointX":0.5,"pointY":0.5}},"layers":[{"animations":[],"layers":[],"texturedRectangle":{"singleTextureOpacity":1,"textXHeight":0.084893023255813951,"textBaseline":0.98719936636991279,"isBackgroundTexture":true,"isVerticalText":false,"textColor":[0,0,0,1],"textureType":6},"initialState":{"affineTransform":[1,0,0,1,0,0],"masksToBounds":false,"rotation":0,"scale":1,"position":{"pointX":345.07256317138672,"pointY":120},"width":685,"sublayerTransform":[1,0,0,0,0,1,0,0,0,0,1,0,0,0,0,1],"contentsRect":{"y":0,"x":0,"width":1,"height":1},"opacity":1,"edgeAntialiasingMask":0,"height":215,"hidden":false,"anchorPoint":{"pointX":0.5,"pointY":0.5}},"texture":"33E3B8D6F9BB46952212E3A2C137759B"}]}]},{"animations":[],"initialState":{"affineTransform":[1,0,0,1,0,0],"masksToBounds":false,"rotation":0,"scale":1,"position":{"pointX":960,"pointY":540},"width":1920,"sublayerTransform":[1,0,0,0,0,1,0,0,0,0,1,0,0,0,0,1],"contentsRect":{"y":0,"x":0,"width":1,"height":1},"opacity":1,"edgeAntialiasingMask":251658240,"height":1080,"hidden":false,"anchorPoint":{"pointX":0.5,"pointY":0.5}},"layers":[{"animations":[],"initialState":{"affineTransform":[1,0,0,1,0,0],"masksToBounds":false,"rotation":0,"scale":1,"position":{"pointX":1072.2609252929688,"pointY":561.15006256103516},"width":571,"sublayerTransform":[1,0,0,0,0,1,0,0,0,0,1,0,0,0,0,1],"contentsRect":{"y":0,"x":0,"width":1,"height":1},"opacity":1,"edgeAntialiasingMask":251658240,"height":1075,"hidden":false,"anchorPoint":{"pointX":0.5,"pointY":0.5}},"objectID":"19EAA004-48BC-4AB6-8E98-2574FCF9A739","layers":[{"animations":[],"layers":[],"texturedRectangle":{"isBackgroundTexture":true,"singleTextureOpacity":1,"textureType":5,"textBaseline":0,"textXHeight":0,"isVerticalText":false},"initialState":{"affineTransform":[1,0,0,1,0,0],"masksToBounds":false,"rotation":0,"scale":1,"position":{"pointX":283.73907470703125,"pointY":535.84993743896484},"width":571,"sublayerTransform":[1,0,0,0,0,1,0,0,0,0,1,0,0,0,0,1],"contentsRect":{"y":0,"x":0,"width":1,"height":1},"opacity":1,"edgeAntialiasingMask":0,"height":1075,"hidden":false,"anchorPoint":{"pointX":0.5,"pointY":0.5}},"texture":"39A9887790E8F93E6D3B349BEE714FFC"}]}]},{"animations":[],"initialState":{"affineTransform":[1,0,0,1,0,0],"masksToBounds":false,"rotation":0,"scale":1,"position":{"pointX":960,"pointY":540},"width":1920,"sublayerTransform":[1,0,0,0,0,1,0,0,0,0,1,0,0,0,0,1],"contentsRect":{"y":0,"x":0,"width":1,"height":1},"opacity":1,"edgeAntialiasingMask":251658240,"height":1080,"hidden":false,"anchorPoint":{"pointX":0.5,"pointY":0.5}},"layers":[{"animations":[],"initialState":{"affineTransform":[1,0,0,1,0,0],"masksToBounds":false,"rotation":0,"scale":1,"position":{"pointX":1608.610107421875,"pointY":541.93820190429688},"width":531,"sublayerTransform":[1,0,0,0,0,1,0,0,0,0,1,0,0,0,0,1],"contentsRect":{"y":0,"x":0,"width":1,"height":1},"opacity":1,"edgeAntialiasingMask":251658240,"height":942,"hidden":false,"anchorPoint":{"pointX":0.5,"pointY":0.5}},"layers":[{"animations":[],"layers":[],"texturedRectangle":{"isBackgroundTexture":true,"singleTextureOpacity":1,"textureType":5,"textBaseline":0,"textXHeight":0,"isVerticalText":false},"initialState":{"affineTransform":[1,0,0,1,0,0],"masksToBounds":false,"rotation":0,"scale":1,"position":{"pointX":264.389892578125,"pointY":469.06179809570312},"width":531,"sublayerTransform":[1,0,0,0,0,1,0,0,0,0,1,0,0,0,0,1],"contentsRect":{"y":0,"x":0,"width":1,"height":1},"opacity":1,"edgeAntialiasingMask":0,"height":942,"hidden":false,"anchorPoint":{"pointX":0.5,"pointY":0.5}},"texture":"2E3956B3E95E6176301E998B6FA0DA28"}]}]},{"animations":[],"initialState":{"affineTransform":[1,0,0,1,0,0],"masksToBounds":false,"rotation":0,"scale":1,"position":{"pointX":960,"pointY":540},"width":1920,"sublayerTransform":[1,0,0,0,0,1,0,0,0,0,1,0,0,0,0,1],"contentsRect":{"y":0,"x":0,"width":1,"height":1},"opacity":1,"edgeAntialiasingMask":251658240,"height":1080,"hidden":false,"anchorPoint":{"pointX":0.5,"pointY":0.5}},"layers":[{"animations":[],"initialState":{"affineTransform":[1,0,0,1,0,0],"masksToBounds":false,"rotation":0,"scale":1,"position":{"pointX":110.91361999511719,"pointY":1007.5},"width":87,"sublayerTransform":[1,0,0,0,0,1,0,0,0,0,1,0,0,0,0,1],"contentsRect":{"y":0,"x":0,"width":1,"height":1},"opacity":1,"edgeAntialiasingMask":251658240,"height":19,"hidden":false,"anchorPoint":{"pointX":0.5,"pointY":0.5}},"layers":[{"animations":[],"layers":[],"texturedRectangle":{"singleTextureOpacity":1,"textXHeight":0.96063157894736839,"textBaseline":0.93409809313322367,"isBackgroundTexture":true,"isVerticalText":false,"textColor":[0.65252357721328735,0.66733616590499878,0.66081053018569946,1],"textureType":6},"initialState":{"affineTransform":[1,0,0,1,0,0],"masksToBounds":false,"rotation":0,"scale":1,"position":{"pointX":48.086380004882812,"pointY":32.5},"width":87,"sublayerTransform":[1,0,0,0,0,1,0,0,0,0,1,0,0,0,0,1],"contentsRect":{"y":0,"x":0,"width":1,"height":1},"opacity":1,"edgeAntialiasingMask":0,"height":19,"hidden":false,"anchorPoint":{"pointX":0.5,"pointY":0.5}},"texture":"3F2A874332E05EB3B623F716EC48D200"}]}]}]}},{"effects":[{"beginTime":0,"baseLayer":{"animations":[],"initialState":{"affineTransform":[1,0,0,1,0,0],"masksToBounds":false,"rotation":0,"scale":1,"position":{"pointX":960,"pointY":540},"width":1920,"sublayerTransform":[1,0,0,0,0,1,0,0,0,0,1,0,0,0,0,1],"contentsRect":{"y":0,"x":0,"width":1,"height":1},"opacity":1,"edgeAntialiasingMask":251658240,"height":1080,"hidden":false,"anchorPoint":{"pointX":0.5,"pointY":0.5}},"objectID":"0","layers":[{"animations":[],"initialState":{"affineTransform":[1,0,0,1,0,0],"masksToBounds":false,"rotation":0,"scale":1,"position":{"pointX":960,"pointY":540},"width":1920,"sublayerTransform":[1,0,0,0,0,1,0,0,0,0,1,-0.00035007912466775983,0,0,0,1],"contentsRect":{"y":0,"x":0,"width":1,"height":1},"opacity":1,"edgeAntialiasingMask":251658240,"height":1080,"hidden":false,"anchorPoint":{"pointX":0.5,"pointY":0.5}},"layers":[{"animations":[],"layers":[],"texturedRectangle":{"isBackgroundTexture":false,"singleTextureOpacity":1,"textureType":0,"textBaseline":0,"textXHeight":0,"isVerticalText":false},"initialState":{"affineTransform":[1,0,0,1,0,0],"masksToBounds":false,"rotation":0,"scale":1,"position":{"pointX":960,"pointY":540},"width":1920,"sublayerTransform":[1,0,0,0,0,1,0,0,0,0,1,0,0,0,0,1],"contentsRect":{"y":0,"x":0,"width":1,"height":1},"opacity":1,"edgeAntialiasingMask":0,"height":1080,"hidden":false,"anchorPoint":{"pointX":0.5,"pointY":0.5}},"texture":"15B6FB6E2B3718897415A5DD6FF7078E"},{"animations":[{"timeOffset":0,"from":{"scalar":false},"beginTime":0,"repeatCount":0,"fillMode":"both","property":"hidden","autoreverses":false,"duration":0.01,"to":{"scalar":true}}],"layers":[],"texturedRectangle":{"isBackgroundTexture":false,"singleTextureOpacity":1,"textureType":0,"textBaseline":0,"textXHeight":0,"isVerticalText":false},"initialState":{"affineTransform":[1,0,0,1,0,0],"masksToBounds":false,"rotation":0,"scale":1,"position":{"pointX":960,"pointY":540},"width":1920,"sublayerTransform":[1,0,0,0,0,1,0,0,0,0,1,0,0,0,0,1],"contentsRect":{"y":0,"x":0,"width":1,"height":1},"opacity":1,"edgeAntialiasingMask":0,"height":1080,"hidden":false,"anchorPoint":{"pointX":0.5,"pointY":0.5}},"texture":"46CC28EA4F4ABA1C058F0FD882325C11"}]}]},"effects":[],"duration":0.01,"type":"transition","attributes":{"direction":0},"name":"none","objectID":"0"}],"automaticPlay":false,"hyperlinks":[],"accessibility":[{"text":"IMG_1015.png","targetRectangle":{"y":70.938201904296875,"x":1343.110107421875,"width":528.52032470703125,"height":938.12359619140625}},{"text":"CelebFeedGesture.mov","targetRectangle":{"y":23.650062561035156,"x":786.76092529296875,"width":567.49139404296875,"height":1071.5928955078125}},{"text":"Validation at low \\u2028fidelities for high ROI","targetRectangle":{"y":52.395637512207031,"x":70.882247924804688,"width":569.07839999999999,"height":144}},{"text":"• • • •","targetRectangle":{"y":1002,"x":71.413619995117188,"width":88.23599999999999,"height":46}},{"text":"A motion prototype meant to convey nuanced gestural interactions. After handing off to a developer we were able to test a coded prototype within the week. ","targetRectangle":{"y":219.5,"x":71.427436828613281,"width":689.32799999999997,"height":230}}],"baseLayer":{"animations":[],"initialState":{"affineTransform":[1,0,0,1,0,0],"masksToBounds":false,"rotation":0,"scale":1,"position":{"pointX":960,"pointY":540},"width":1920,"sublayerTransform":[1,0,0,0,0,1,0,0,0,0,1,0,0,0,0,1],"contentsRect":{"y":0,"x":0,"width":1,"height":1},"opacity":1,"edgeAntialiasingMask":251658240,"height":1080,"hidden":false,"anchorPoint":{"pointX":0.5,"pointY":0.5}},"objectID":"0","layers":[{"animations":[],"initialState":{"affineTransform":[1,0,0,1,0,0],"masksToBounds":false,"rotation":0,"scale":1,"position":{"pointX":960,"pointY":540},"width":1920,"sublayerTransform":[1,0,0,0,0,1,0,0,0,0,1,-0.00035007912466775983,0,0,0,1],"contentsRect":{"y":0,"x":0,"width":1,"height":1},"opacity":1,"edgeAntialiasingMask":251658240,"height":1080,"hidden":false,"anchorPoint":{"pointX":0.5,"pointY":0.5}},"layers":[{"animations":[],"layers":[],"texturedRectangle":{"isBackgroundTexture":false,"singleTextureOpacity":1,"textureType":0,"textBaseline":0,"textXHeight":0,"isVerticalText":false},"initialState":{"affineTransform":[1,0,0,1,0,0],"masksToBounds":false,"rotation":0,"scale":1,"position":{"pointX":960,"pointY":540},"width":1920,"sublayerTransform":[1,0,0,0,0,1,0,0,0,0,1,0,0,0,0,1],"contentsRect":{"y":0,"x":0,"width":1,"height":1},"opacity":1,"edgeAntialiasingMask":0,"height":1080,"hidden":false,"anchorPoint":{"pointX":0.5,"pointY":0.5}},"texture":"46CC28EA4F4ABA1C058F0FD882325C11"}]}]}}]}